{
  "appPageId" : "604475ba-e99d-46b7-9880-6c0a08096106",
  "componentName" : "siteforce:sldsOneColLayout",
  "dataProviders" : [ ],
  "id" : "9029bc71-786c-4919-91f5-c1f3d7164131",
  "label" : "File Related List",
  "regions" : [ {
    "id" : "af21a727-0a17-4095-9ae0-190db28569e2",
    "regionName" : "header",
    "type" : "region"
  }, {
    "components" : [ {
      "componentAttributes" : {
        "customTitle" : "",
        "parentRecordId" : "{!recordId}",
        "relatedListName" : "{!relationshipApiName}",
        "showBreadCrumbs" : true,
        "showCustomTitle" : false,
        "showManualRefreshButton" : true,
        "showRowNumbers" : true
      },
      "componentName" : "forceCommunity:relatedList",
      "id" : "d708c81e-97c7-4a3b-b6a0-abfcae4f1492",
      "renderPriority" : "NEUTRAL",
      "renditionMap" : { },
      "type" : "component"
    } ],
    "id" : "927d2967-a3ba-42a0-856b-e1cc8369f07d",
    "regionName" : "content",
    "type" : "region"
  }, {
    "id" : "b9771cd8-9d32-4ab6-b5f3-584b5fc7f1be",
    "regionName" : "footer",
    "type" : "region"
  } ],
  "themeLayoutType" : "Inner",
  "type" : "view",
  "viewType" : "relatedlist-069"
}